{
  "lineToGraph": "Równanie prostej:",
  "saveLine": "Zatwierdź wykres",
  "setThePoint": "Ustal punkt",
  "yourLine": "Twój wykres:",
  "slopeIs": "{0} =",
  "undefined": "nieokreślone",
  "notALine": "... nie jest prostoliniowy",
  "graphTheLine": "Ustal wykres",
  "tab.slopeIntercept": "Punkt na osi OY-Nachylenie",
  "slope": "Współczynnik kierunkowy",
  "tab.lineGame": "Analizuj wykres",
  "putPointsOnLine": "Umieść punkty na prostej",
  "slopeUndefined": "{0}={1} (współczynnik kierunkowy nieokreślony)",
  "makeTheEquation": "Utwórz równanie",
  "hideLines": "Ukryj wykres",
  "tab.slope": "Nachylenie",
  "tab.pointSlope": "Punkt-Nachylenie",
  "translation.credits": "Andrzej Batorski",
  "eraseLines": "Wymaż wykres",
  "yourEquation": "Twoje równanie",
  "setTheSlope": "Ustal współczynnik kierunkowy (lub nachylenie)",
  "aCorrectEquation": "Prawidłowe równanie:",
  "graphing-lines.name": "Wykresy prostych",
  "setTheYIntercept": "Ustal wyraz wolny (lub punkt wspólny z OY)"
}